{
  "columns": [
    {
      "name": "numeroNF",
      "label": "Número NF",
      "field": "numeroNF",
      "align": "center"
    },
    {
      "name": "dataInicio",
      "label": "Período De",
      "field": "dataInicio",
      "align": "center"
    },
    {
      "name": "dataFim",
      "label": "Período Até",
      "field": "dataFim",
      "align": "center"
    },
    {
      "name": "nomeCliente",
      "label": "Nome Completo",
      "field": "nomeCliente",
      "align": "center"
    },
    {
      "name": "documento",
      "label": "CNPJ/CPF",
      "field": "documento",
      "align": "center"
    },
    {
      "name": "acoes",
      "label": "Ações",
      "field": "acoes",
      "align": "center"
    }
  ]
}
